wllegal/__init__.py
wllegal/apps.py
wllegal/models.py
wllegal/settings_test.py
wllegal/tests.py
wllegal/locale/django.pot
wllegal/locale/ab/LC_MESSAGES/django.mo
wllegal/locale/ab/LC_MESSAGES/django.po
wllegal/locale/af/LC_MESSAGES/django.mo
wllegal/locale/af/LC_MESSAGES/django.po
wllegal/locale/afh/LC_MESSAGES/django.mo
wllegal/locale/afh/LC_MESSAGES/django.po
wllegal/locale/ang/LC_MESSAGES/django.mo
wllegal/locale/ang/LC_MESSAGES/django.po
wllegal/locale/ar/LC_MESSAGES/django.mo
wllegal/locale/ar/LC_MESSAGES/django.po
wllegal/locale/ar_LY/LC_MESSAGES/django.mo
wllegal/locale/ar_LY/LC_MESSAGES/django.po
wllegal/locale/ars/LC_MESSAGES/django.mo
wllegal/locale/ars/LC_MESSAGES/django.po
wllegal/locale/ast/LC_MESSAGES/django.mo
wllegal/locale/ast/LC_MESSAGES/django.po
wllegal/locale/awa/LC_MESSAGES/django.mo
wllegal/locale/awa/LC_MESSAGES/django.po
wllegal/locale/az/LC_MESSAGES/django.mo
wllegal/locale/az/LC_MESSAGES/django.po
wllegal/locale/ba/LC_MESSAGES/django.mo
wllegal/locale/ba/LC_MESSAGES/django.po
wllegal/locale/bar/LC_MESSAGES/django.mo
wllegal/locale/bar/LC_MESSAGES/django.po
wllegal/locale/be/LC_MESSAGES/django.mo
wllegal/locale/be/LC_MESSAGES/django.po
wllegal/locale/be_Latn/LC_MESSAGES/django.mo
wllegal/locale/be_Latn/LC_MESSAGES/django.po
wllegal/locale/ber/LC_MESSAGES/django.mo
wllegal/locale/ber/LC_MESSAGES/django.po
wllegal/locale/bg/LC_MESSAGES/django.mo
wllegal/locale/bg/LC_MESSAGES/django.po
wllegal/locale/bn/LC_MESSAGES/django.mo
wllegal/locale/bn/LC_MESSAGES/django.po
wllegal/locale/bn_BD/LC_MESSAGES/django.mo
wllegal/locale/bn_BD/LC_MESSAGES/django.po
wllegal/locale/bnt/LC_MESSAGES/django.mo
wllegal/locale/bnt/LC_MESSAGES/django.po
wllegal/locale/bo/LC_MESSAGES/django.mo
wllegal/locale/bo/LC_MESSAGES/django.po
wllegal/locale/br/LC_MESSAGES/django.mo
wllegal/locale/br/LC_MESSAGES/django.po
wllegal/locale/ca/LC_MESSAGES/django.mo
wllegal/locale/ca/LC_MESSAGES/django.po
wllegal/locale/ce/LC_MESSAGES/django.mo
wllegal/locale/ce/LC_MESSAGES/django.po
wllegal-2025.9.dist-info/licenses/LICENSE
wllegal-2025.9.dist-info/METADATA
wllegal-2025.9.dist-info/WHEEL
wllegal-2025.9.dist-info/top_level.txt
wllegal-2025.9.dist-info/RECORD
