Metadata-Version: 2.4
Name: wllegal
Version: 2025.9
Summary: Hosted Weblate legal stuff
Author-email: Michal Čihař <michal@weblate.org>
License-Expression: GPL-3.0-or-later
Project-URL: Documentation, https://docs.weblate.org/
Project-URL: Download, https://github.com/WeblateOrg/wllegal
Project-URL: Funding, https://weblate.org/donate/
Project-URL: Homepage, https://weblate.org/
Project-URL: Issue Tracker, https://github.com/WeblateOrg/wllegal/issues
Project-URL: Source Code, https://github.com/WeblateOrg/wllegal
Project-URL: Twitter, https://twitter.com/WeblateOrg
Keywords: i18n,l10n,gettext,git,mercurial,translate
Platform: any
Classifier: Development Status :: 5 - Production/Stable
Classifier: Environment :: Web Environment
Classifier: Framework :: Django
Classifier: Intended Audience :: Developers
Classifier: Intended Audience :: System Administrators
Classifier: Operating System :: OS Independent
Classifier: Programming Language :: Python
Classifier: Programming Language :: Python :: 3
Classifier: Programming Language :: Python :: 3 :: Only
Classifier: Programming Language :: Python :: 3.11
Classifier: Programming Language :: Python :: 3.12
Classifier: Programming Language :: Python :: 3.13
Classifier: Topic :: Software Development :: Internationalization
Classifier: Topic :: Software Development :: Localization
Classifier: Topic :: Internet :: WWW/HTTP
Classifier: Topic :: Internet :: WWW/HTTP :: Dynamic Content
Requires-Python: >=3.11
License-File: LICENSE
Requires-Dist: Django<6.1,>=5.2
Requires-Dist: weblate-language-data>=2025.9
Provides-Extra: dev
Requires-Dist: wllegal[lint,test]; extra == "dev"
Provides-Extra: lint
Requires-Dist: pre-commit==4.5.0; extra == "lint"
Provides-Extra: test
Requires-Dist: wllegal[weblate]; extra == "test"
Requires-Dist: coverage==7.13.0; extra == "test"
Requires-Dist: translate-toolkit; extra == "test"
Provides-Extra: weblate
Requires-Dist: Weblate[postgres]>=5.0; extra == "weblate"
Dynamic: license-file
